hzexcel/__init__.py
hzexcel/example.py
hzexcel/export_excel.py
hzexcel/file.py
hzexcel/import_excel.py
hzexcel-0.0.13.dist-info/METADATA
hzexcel-0.0.13.dist-info/WHEEL
hzexcel-0.0.13.dist-info/licenses/LICENSE
hzexcel-0.0.13.dist-info/RECORD
