Metadata-Version: 2.1
Name: hzexcel
Version: 0.0.13
Summary: 提供常用django、Python后端的excel导入导出功能
Project-URL: Homepage, https://github.com/pypa/sampleproject
Project-URL: Bug Tracker, https://github.com/pypa/sampleproject/issues
Author-email: myliao Nathen <1739951529@qq.com>
License-File: LICENSE
Classifier: License :: OSI Approved :: MIT License
Classifier: Operating System :: OS Independent
Classifier: Programming Language :: Python :: 3
Requires-Python: >=3.7
